[
    {
        "artist": {
            "mbid": "",
            "#text": "Black Milk"
        },
        "image": [
            {
                "size": "small",
                "#text": "https://lastfm.freetls.fastly.net/i/u/34s/2a96cbd8b46e442fc41c2b86b821562f.png"
            },
            {
                "size": "medium",
                "#text": "https://lastfm.freetls.fastly.net/i/u/64s/2a96cbd8b46e442fc41c2b86b821562f.png"
            },
            {
                "size": "large",
                "#text": "https://lastfm.freetls.fastly.net/i/u/174s/2a96cbd8b46e442fc41c2b86b821562f.png"
            }
        ],
        "mbid": "",
        "url": "https://www.last.fm/music/Black+Milk/_/Act+Like",
        "name": "Act Like",
        "@attr": {
            "rank": "1"
        },
        "playcount": "2"
    },
    {
        "artist": {
            "mbid": "1551ab5e-66d8-4b8f-9221-b73271d8c046",
            "#text": "Oso Leone"
        },
        "image": [
            {
                "size": "small",
                "#text": "https://lastfm.freetls.fastly.net/i/u/34s/2a96cbd8b46e442fc41c2b86b821562f.png"
            },
            {
                "size": "medium",
                "#text": "https://lastfm.freetls.fastly.net/i/u/64s/2a96cbd8b46e442fc41c2b86b821562f.png"
            },
            {
                "size": "large",
                "#text": "https://lastfm.freetls.fastly.net/i/u/174s/2a96cbd8b46e442fc41c2b86b821562f.png"
            }
        ],
        "mbid": "38027b02-f792-458b-8982-3157f41244a3",
        "url": "https://www.last.fm/music/Oso+Leone/_/Virtual+U",
        "name": "Virtual U",
        "@attr": {
            "rank": "2"
        },
        "playcount": "2"
    },
    {
        "artist": {
            "mbid": "",
            "#text": "Pluma"
        },
        "image": [
            {
                "size": "small",
                "#text": "https://lastfm.freetls.fastly.net/i/u/34s/2a96cbd8b46e442fc41c2b86b821562f.png"
            },
            {
                "size": "medium",
                "#text": "https://lastfm.freetls.fastly.net/i/u/64s/2a96cbd8b46e442fc41c2b86b821562f.png"
            },
            {
                "size": "large",
                "#text": "https://lastfm.freetls.fastly.net/i/u/174s/2a96cbd8b46e442fc41c2b86b821562f.png"
            }
        ],
        "mbid": "",
        "url": "https://www.last.fm/music/Pluma/_/Quando+Eu+T%C3%B4+Perto",
        "name": "Quando Eu T\u00f4 Perto",
        "@attr": {
            "rank": "3"
        },
        "playcount": "2"
    },
    {
        "artist": {
            "mbid": "68c6d24f-1750-485b-9763-59cf7ca2a6b1",
            "#text": "\u732b \u30b7 Corp."
        },
        "image": [
            {
                "size": "small",
                "#text": "https://lastfm.freetls.fastly.net/i/u/34s/2a96cbd8b46e442fc41c2b86b821562f.png"
            },
            {
                "size": "medium",
                "#text": "https://lastfm.freetls.fastly.net/i/u/64s/2a96cbd8b46e442fc41c2b86b821562f.png"
            },
            {
                "size": "large",
                "#text": "https://lastfm.freetls.fastly.net/i/u/174s/2a96cbd8b46e442fc41c2b86b821562f.png"
            }
        ],
        "mbid": "d42dc111-d79a-4c59-b063-b720255e8b21",
        "url": "https://www.last.fm/music/%E7%8C%AB+%E3%82%B7+Corp./_/Anubias",
        "name": "Anubias",
        "@attr": {
            "rank": "4"
        },
        "playcount": "2"
    },
    {
        "artist": {
            "mbid": "",
            "#text": "Ahwlee"
        },
        "image": [
            {
                "size": "small",
                "#text": "https://lastfm.freetls.fastly.net/i/u/34s/2a96cbd8b46e442fc41c2b86b821562f.png"
            },
            {
                "size": "medium",
                "#text": "https://lastfm.freetls.fastly.net/i/u/64s/2a96cbd8b46e442fc41c2b86b821562f.png"
            },
            {
                "size": "large",
                "#text": "https://lastfm.freetls.fastly.net/i/u/174s/2a96cbd8b46e442fc41c2b86b821562f.png"
            }
        ],
        "mbid": "cbc8121e-167a-41a2-aa0b-2cb9d64439e1",
        "url": "https://www.last.fm/music/Ahwlee/_/callyourmom+%7C+cloud(smile;often)",
        "name": "callyourmom | cloud(smile;often)",
        "@attr": {
            "rank": "5"
        },
        "playcount": "1"
    }
]